vastbase/psycopg2/__init__.py
vastbase/psycopg2/floatvector.py
vastbase/psycopg2/register.py
vastbase/sqlalchemy/__init__.py
vastbase/sqlalchemy/floatvector.py
vastbase/sqlalchemy/functions.py
vastbase/utils/__init__.py
vastbase/utils/vector.py
pyvector_vastbase-1.0.2.dist-info/METADATA
pyvector_vastbase-1.0.2.dist-info/WHEEL
pyvector_vastbase-1.0.2.dist-info/top_level.txt
pyvector_vastbase-1.0.2.dist-info/RECORD
