Metadata-Version: 2.2
Name: pyvector-vastbase
Version: 1.0.2
Summary: pyvector support for vastbase
Author-email: wangxiaoyang <wangxiaoyang@vastdata.com.cn>
License: MIT
Project-URL: Homepage, https://www.vastbase.com.cn
Requires-Python: >=3.8
Requires-Dist: numpy
